pwpush/__init__.py
pwpush/__main__.py
pwpush/commands/config.py
pwpush/options.py
pwpush/py.typed
pwpush-0.11.0.dist-info/LICENSE
pwpush-0.11.0.dist-info/METADATA
pwpush-0.11.0.dist-info/WHEEL
pwpush-0.11.0.dist-info/entry_points.txt
pwpush-0.11.0.dist-info/RECORD
