Metadata-Version: 2.3
Name: pwpush
Version: 0.11.0
Summary: Command Line Interface to Password Pusher.
License: MIT
Keywords: security,cli,password,sharing
Author: pwpush
Author-email: pglombardo@hey.com
Requires-Python: >=3.9.2,<4.0
Classifier: Development Status :: 3 - Alpha
Classifier: Intended Audience :: Developers
Classifier: Intended Audience :: Information Technology
Classifier: Intended Audience :: System Administrators
Classifier: Intended Audience :: Financial and Insurance Industry
Classifier: Operating System :: OS Independent
Classifier: Topic :: Software Development :: Libraries :: Python Modules
Classifier: Topic :: Security
Classifier: License :: OSI Approved :: MIT License
Classifier: Programming Language :: Python :: 3
Classifier: Programming Language :: Python :: 3.8
Classifier: Programming Language :: Python :: 3.9
Classifier: Programming Language :: Python :: 3.10
Classifier: Programming Language :: Python :: 3.11
Requires-Dist: importlib_metadata (>=4.5,<7.0) ; python_version < "3.8"
Requires-Dist: python-dateutil (>=2.8.2,<3.0.0)
Requires-Dist: requests (>=2.28.1,<3.0.0)
Requires-Dist: rich (>=12.5.1,<14.0.0)
Requires-Dist: shellingham (>=1.5.0,<2.0.0)
Requires-Dist: typer[all] (>=0.6.1,<0.16.0)
Requires-Dist: xkcdpass (==1.19.9)
Project-URL: Homepage, https://github.com/pglombardo/pwpush
Project-URL: Repository, https://github.com/pglombardo/pwpush
